Workbook

Sheet 01_Start_Here
A1: =HYPERLINK("#01_Start_Here!A1", "🏠 Start") | B1: =HYPERLINK("#02_Dashboard!A1", "📊 Dashboard") | C1: =HYPERLINK("#03_Holdings!A1", "💼 Holdings") | D1: =HYPERLINK("#04_Transactions!A1", "📑 Ledger") | E1: =HYPERLINK("#05_Performance!A1", "📈 Performance") | F1: =HYPERLINK("#06_Allocation_Risk!A1", "🎯 Allocation") | G1: =HYPERLINK("#07_Dividends_Income!A1", "💰 Dividends") | H1: =HYPERLINK("#08_Goals_SIP!A1", "🎯 Goals") | I1: =HYPERLINK("#09_Rebalancing_Drift!A1", "⚖️ Rebalance") | J1: =HYPERLINK("#10_Scenarios_Freedom!A1", "🚀 What-If") | K1: =HYPERLINK("#11_Reviews_Reports!A1", "📋 Reports") | L1: =HYPERLINK("#12_Investment_Journal!A1", "📓 Journal") | M1: =HYPERLINK("#13_Settings_Assumptions!A1", "⚙️ Settings")
A3: ULTIMATE PRO INVESTMENT MANAGEMENT SUITE V2.0
A4: Institutional-Grade Digital Portfolio Tracking & Analytics Template for Excel
A6: WELCOME TO YOUR PERSONAL INVESTMENT MANAGEMENT SYSTEM
A7: WHAT THIS TRACKER DOES
A8: Consolidates all your Stocks, ETFs, Mutual Funds, Bonds, REITs, Gold, and Cash in one automated dashboard. Tracks real-time cost basis, realized/unrealized P&L, portfolio dividends, rebalancing drift, historical performance, and financial freedom goals without macros or external API dependencies.
A10: HOW TO ENTER DATA
A11: 1. Enter initial portfolio holdings in '03_Holdings' (or explore with preloaded demo data). 2. Record buys, sells, splits, and deposits in '04_Transactions'. 3. Update Current Market Prices in '03_Holdings' periodically (weekly/monthly). 4. All KPIs, allocations, rebalancing suggestions, and charts calculate automatically!
A13: AUTOMATED CALCULATIONS
A14: Unrealized P/L = Current Value − Cost Basis. Realized P/L = Sale Proceeds − Applicable Cost Basis − Fees/Taxes. TWR (Time-Weighted Return) = Evaluates organic investment skill independent of cash flows. MWR / XIRR = Measures your personal dollar-weighted annualized return including cash timing. Cost Basis Assumed: Weighted Average Cost (WAC) methodology.
A16: IMPORTANT ASSUMPTIONS & PRIVACY
A17: • PRIVACY-FIRST: Absolutely NO passwords, brokerage logins, OTPs, or API keys are required. • All calculations execute locally inside Microsoft Excel. • Educational Template: Not personalized financial, legal, or tax advice. • Currency symbol can be customized in '13_Settings_Assumptions' (USD $, INR ₹, EUR €, GBP £).
A19: WORKBOOK CELL COLOR CONVENTIONS
A20: EDITABLE CELLS | B20: Enter your investment tickers, quantities, purchase prices, and transactions here.
A21: AUTOMATIC CALCULATIONS | B21: Formulas calculate automatically. Do not manually overwrite these cells.
A22: ALERT / DRIFT STATUS | B22: Identifies allocation drift, missed contributions, or items requiring your attention.
A23: KPI & HIGHLIGHT METRICS | B23: Key summaries, portfolio values, and return metrics.
A25: NEED A CUSTOM VERSION OR SPECIALIZED EXCEL ENGINEERING?
A26: Custom Parade Seat बनवाने के लिए सहायता चाहिए? संपर्क करें: 📱 WhatsApp: +91 95094 75762 ✈️ Telegram: https://t.me/V_sangwal 📸 Instagram: https://www.instagram.com/vikas_sangwal_05/ 💼 LinkedIn: https://www.linkedin.com/in/vikassangwal अपनी आवश्यकता के साथ सीधे संपर्क करें।

Sheet 02_Dashboard
A1: =HYPERLINK("#01_Start_Here!A1", "🏠 Start") | B1: =HYPERLINK("#02_Dashboard!A1", "📊 Dashboard") | C1: =HYPERLINK("#03_Holdings!A1", "💼 Holdings") | D1: =HYPERLINK("#04_Transactions!A1", "📑 Ledger") | E1: =HYPERLINK("#05_Performance!A1", "📈 Performance") | F1: =HYPERLINK("#06_Allocation_Risk!A1", "🎯 Allocation") | G1: =HYPERLINK("#07_Dividends_Income!A1", "💰 Dividends") | H1: =HYPERLINK("#08_Goals_SIP!A1", "🎯 Goals") | I1: =HYPERLINK("#09_Rebalancing_Drift!A1", "⚖️ Rebalance") | J1: =HYPERLINK("#10_Scenarios_Freedom!A1", "🚀 What-If") | K1: =HYPERLINK("#11_Reviews_Reports!A1", "📋 Reports") | L1: =HYPERLINK("#12_Investment_Journal!A1", "📓 Journal") | M1: =HYPERLINK("#13_Settings_Assumptions!A1", "⚙️ Settings")
A3: PORTFOLIO MASTER DASHBOARD
A4: Real-Time Executive Wealth Intelligence, Allocation & Risk Performance
A6: CURRENT PORTFOLIO VALUE | D6: TOTAL INVESTED CAPITAL | G6: UNREALIZED PROFIT / LOSS | J6: TOTAL RETURN %
A7: ='03_Holdings'!M6 | D7: ='03_Holdings'!L6 | G7: ='03_Holdings'!N6 | J7: ='03_Holdings'!O6
A8: Total Market Value + Cash | D8: Net Capital Put to Work | G8: Open Gains (Excl. Realized) | J8: Lifetime Portfolio Performance
A10: ANNUALIZED RETURN (CAGR) | D10: REALIZED P/L (CLOSED TRADES) | G10: TOTAL DIVIDENDS COLLECTED | J10: CASH & EQUIVALENTS
A11: ='05_Performance'!F24 | D11: ='04_Transactions'!L6 | G11: ='07_Dividends_Income'!G6 | J11: ='03_Holdings'!M22
A12: Compound Annual Growth | D12: Booked Gains from Ledger | G12: Cumulative Passive Income | J12: Dry Powder & Liquid Capital
A14: 💡 AUTOMATED SMART PORTFOLIO INSIGHTS
A15: ="• PORTFOLIO PERFORMANCE: Total unrealized gain is " & TEXT('03_Holdings'!N6, "$#,##0") & " (" & TEXT('03_Holdings'!O6, "+0.0%") & ") across " & COUNTA('03_Holdings'!B8:B22) & " active positions."
A16: ="• ALLOCATION BALANCE: Equities represent " & TEXT('06_Allocation_Risk'!C8, "0.0%") & " of total capital, currently " & IF('06_Allocation_Risk'!E8>0, "overweight target by " & TEXT('06_Allocation_Risk'!E8, "0.0%"), "within target boundaries") & "."
A17: ="• CASH POSITION: Dry powder stands at " & TEXT('03_Holdings'!M22, "$#,##0") & " (" & TEXT('06_Allocation_Risk'!C13, "0.0%") & " of portfolio), ensuring liquidity for opportunistic buys."
A18: ="• DIVIDEND RUN-RATE: Cumulative passive income collected is " & TEXT('07_Dividends_Income'!G6, "$#,##0") & " with current portfolio dividend yield of " & TEXT('07_Dividends_Income'!K6, "0.00%") & "."
A20: ASSET ALLOCATION BREAKDOWN | G20: TOP HOLDINGS BY MARKET VALUE
A21: Asset Class | B21: Current Value | C21: Weight % | D21: Target % | E21: Drift % | G21: Rank | H21: Holding | I21: Ticker | J21: Current Value | K21: Weight % | L21: Return %
A22: Stocks (Equities) | B22: ='06_Allocation_Risk'!B8 | C22: ='06_Allocation_Risk'!C8 | D22: ='06_Allocation_Risk'!D8 | E22: ='06_Allocation_Risk'!E8 | G22: #1 | H22: ='03_Holdings'!B8 | I22: ='03_Holdings'!C8 | J22: ='03_Holdings'!M8 | K22: ='03_Holdings'!P8 | L22: ='03_Holdings'!O8
A23: ETFs & Index Funds | B23: ='06_Allocation_Risk'!B9 | C23: ='06_Allocation_Risk'!C9 | D23: ='06_Allocation_Risk'!D9 | E23: ='06_Allocation_Risk'!E9 | G23: #2 | H23: ='03_Holdings'!B9 | I23: ='03_Holdings'!C9 | J23: ='03_Holdings'!M9 | K23: ='03_Holdings'!P9 | L23: ='03_Holdings'!O9
A24: Fixed Income / Bonds | B24: ='06_Allocation_Risk'!B10 | C24: ='06_Allocation_Risk'!C10 | D24: ='06_Allocation_Risk'!D10 | E24: ='06_Allocation_Risk'!E10 | G24: #3 | H24: ='03_Holdings'!B10 | I24: ='03_Holdings'!C10 | J24: ='03_Holdings'!M10 | K24: ='03_Holdings'!P10 | L24: ='03_Holdings'!O10
A25: Real Estate (REITs) | B25: ='06_Allocation_Risk'!B11 | C25: ='06_Allocation_Risk'!C11 | D25: ='06_Allocation_Risk'!D11 | E25: ='06_Allocation_Risk'!E11 | G25: #4 | H25: ='03_Holdings'!B11 | I25: ='03_Holdings'!C11 | J25: ='03_Holdings'!M11 | K25: ='03_Holdings'!P11 | L25: ='03_Holdings'!O11
A26: Gold & Commodities | B26: ='06_Allocation_Risk'!B12 | C26: ='06_Allocation_Risk'!C12 | D26: ='06_Allocation_Risk'!D12 | E26: ='06_Allocation_Risk'!E12 | G26: #5 | H26: ='03_Holdings'!B12 | I26: ='03_Holdings'!C12 | J26: ='03_Holdings'!M12 | K26: ='03_Holdings'!P12 | L26: ='03_Holdings'!O12
A27: Cash & Equivalents | B27: ='06_Allocation_Risk'!B13 | C27: ='06_Allocation_Risk'!C13 | D27: ='06_Allocation_Risk'!D13 | E27: ='06_Allocation_Risk'!E13

Sheet 03_Holdings
A1: =HYPERLINK("#01_Start_Here!A1", "🏠 Start") | B1: =HYPERLINK("#02_Dashboard!A1", "📊 Dashboard") | C1: =HYPERLINK("#03_Holdings!A1", "💼 Holdings") | D1: =HYPERLINK("#04_Transactions!A1", "📑 Ledger") | E1: =HYPERLINK("#05_Performance!A1", "📈 Performance") | F1: =HYPERLINK("#06_Allocation_Risk!A1", "🎯 Allocation") | G1: =HYPERLINK("#07_Dividends_Income!A1", "💰 Dividends") | H1: =HYPERLINK("#08_Goals_SIP!A1", "🎯 Goals") | I1: =HYPERLINK("#09_Rebalancing_Drift!A1", "⚖️ Rebalance") | J1: =HYPERLINK("#10_Scenarios_Freedom!A1", "🚀 What-If") | K1: =HYPERLINK("#11_Reviews_Reports!A1", "📋 Reports") | L1: =HYPERLINK("#12_Investment_Journal!A1", "📓 Journal") | M1: =HYPERLINK("#13_Settings_Assumptions!A1", "⚙️ Settings")
A3: HOLDINGS DATABASE & COST BASIS TRACKER
A4: Comprehensive Multi-Asset Portfolio Holdings with Automated P/L & Weight Tracking
A6: PORTFOLIO TOTALS & AGGREGATE PERFORMANCE | L6: =SUM(L8:L25) | M6: =SUM(M8:M25) | N6: =M6-L6 | O6: =IFERROR(N6/L6, 0) | P6: =SUM(P8:P25) | Q6: Target Sum: =SUM(Q8:Q25)
A7: ID | B7: Asset Name | C7: Ticker | D7: Asset Type | E7: Sector | F7: Industry | G7: Country | H7: Broker / Account | I7: Quantity | J7: Avg Buy Price | K7: Current Price | L7: Invested Cost | M7: Current Value | N7: Unrealized P/L | O7: Return % | P7: Weight % | Q7: Target % | R7: Drift % | S7: First Purchased | T7: Investment Notes
A8: INV-001 | B8: Apple Inc. | C8: AAPL | D8: Stocks | E8: Technology | F8: Consumer Electronics | G8: United States | H8: Fidelity | I8: 85 | J8: 175.5 | K8: 224.23 | L8: =I8*J8 | M8: =I8*K8 | N8: =M8-L8 | O8: =IFERROR(N8/L8, 0) | P8: =IFERROR(M8/$M$6, 0) | Q8: 0.09 | R8: =P8-Q8 | S8: 2023-01-15 | T8: Core tech ecosystem compounder
A9: INV-002 | B9: Microsoft Corp. | C9: MSFT | D9: Stocks | E9: Technology | F9: Software Infrastructure | G9: United States | H9: Fidelity | I9: 45 | J9: 340.2 | K9: 448.37 | L9: =I9*J9 | M9: =I9*K9 | N9: =M9-L9 | O9: =IFERROR(N9/L9, 0) | P9: =IFERROR(M9/$M$6, 0) | Q9: 0.1 | R9: =P9-Q9 | S9: 2023-02-10 | T9: Cloud Azure & Enterprise AI leader
A10: INV-003 | B10: Alphabet Inc. | C10: GOOGL | D10: Stocks | E10: Communication | F10: Internet & Advertising | G10: United States | H10: Charles Schwab | I10: 70 | J10: 132.8 | K10: 168.45 | L10: =I10*J10 | M10: =I10*K10 | N10: =M10-L10 | O10: =IFERROR(N10/L10, 0) | P10: =IFERROR(M10/$M$6, 0) | Q10: 0.06 | R10: =P10-Q10 | S10: 2023-04-12 | T10: Search monopoly + YouTube + DeepMind
A11: INV-004 | B11: NVIDIA Corporation | C11: NVDA | D11: Stocks | E11: Technology | F11: Semiconductors | G11: United States | H11: Interactive Brokers | I11: 120 | J11: 48.5 | K11: 118.9 | L11: =I11*J11 | M11: =I11*K11 | N11: =M11-L11 | O11: =IFERROR(N11/L11, 0) | P11: =IFERROR(M11/$M$6, 0) | Q11: 0.07 | R11: =P11-Q11 | S11: 2023-06-20 | T11: AI hardware accelerator standard
A12: INV-005 | B12: Vanguard S&P 500 ETF | C12: VOO | D12: ETFs | E12: Broad Market | F12: Large Cap Blend | G12: United States | H12: Fidelity | I12: 110 | J12: 410 | K12: 512.4 | L12: =I12*J12 | M12: =I12*K12 | N12: =M12-L12 | O12: =IFERROR(N12/L12, 0) | P12: =IFERROR(M12/$M$6, 0) | Q12: 0.25 | R12: =P12-Q12 | S12: 2022-11-05 | T12: Core low-cost broad index holding
A13: INV-006 | B13: Invesco QQQ Trust | C13: QQQ | D13: ETFs | E13: Technology Blend | F13: Nasdaq-100 Large Cap | G13: United States | H13: Charles Schwab | I13: 50 | J13: 375 | K13: 478.1 | L13: =I13*J13 | M13: =I13*K13 | N13: =M13-L13 | O13: =IFERROR(N13/L13, 0) | P13: =IFERROR(M13/$M$6, 0) | Q13: 0.11 | R13: =P13-Q13 | S13: 2023-03-18 | T13: Tech & growth tilt index
A14: INV-007 | B14: Vanguard Total Intl Stock | C14: VXUS | D14: ETFs | E14: International | F14: All-World ex-US | G14: Global | H14: Fidelity | I14: 160 | J14: 54.2 | K14: 62.8 | L14: =I14*J14 | M14: =I14*K14 | N14: =M14-L14 | O14: =IFERROR(N14/L14, 0) | P14: =IFERROR(M14/$M$6, 0) | Q14: 0.05 | R14: =P14-Q14 | S14: 2023-05-14 | T14: International developed & emerging
A15: INV-008 | B15: Vanguard Total Bond Market | C15: BND | D15: Bonds | E15: Fixed Income | F15: Investment Grade Bonds | G15: United States | H15: Fidelity | I15: 180 | J15: 72.5 | K15: 73.1 | L15: =I15*J15 | M15: =I15*K15 | N15: =M15-L15 | O15: =IFERROR(N15/L15, 0) | P15: =IFERROR(M15/$M$6, 0) | Q15: 0.06 | R15: =P15-Q15 | S15: 2023-07-22 | T15: Capital preservation & ballast
A16: INV-009 | B16: US Treasury 7-10Y Bond | C16: IEF | D16: Bonds | E16: Government | F16: Intermediate Treasuries | G16: United States | H16: Charles Schwab | I16: 75 | J16: 94.2 | K16: 95.8 | L16: =I16*J16 | M16: =I16*K16 | N16: =M16-L16 | O16: =IFERROR(N16/L16, 0) | P16: =IFERROR(M16/$M$6, 0) | Q16: 0.03 | R16: =P16-Q16 | S16: 2023-08-01 | T16: Sovereign liquidity hedge
A17: INV-010 | B17: Realty Income Corp. | C17: O | D17: REITs | E17: Real Estate | F17: Net Lease Retail | G17: United States | H17: Interactive Brokers | I17: 150 | J17: 52.3 | K17: 53.6 | L17: =I17*J17 | M17: =I17*K17 | N17: =M17-L17 | O17: =IFERROR(N17/L17, 0) | P17: =IFERROR(M17/$M$6, 0) | Q17: 0.04 | R17: =P17-Q17 | S17: 2023-09-10 | T17: Monthly dividend company
A18: INV-011 | B18: Prologis Inc. | C18: PLD | D18: REITs | E18: Real Estate | F18: Industrial Logistics | G18: United States | H18: Charles Schwab | I18: 40 | J18: 118 | K18: 122.4 | L18: =I18*J18 | M18: =I18*K18 | N18: =M18-L18 | O18: =IFERROR(N18/L18, 0) | P18: =IFERROR(M18/$M$6, 0) | Q18: 0.02 | R18: =P18-Q18 | S18: 2023-10-15 | T18: Global logistics & warehousing
A19: INV-012 | B19: SPDR Gold Shares | C19: GLD | D19: Gold | E19: Commodities | F19: Precious Metals | G19: Global | H19: Fidelity | I19: 40 | J19: 185 | K19: 231.5 | L19: =I19*J19 | M19: =I19*K19 | N19: =M19-L19 | O19: =IFERROR(N19/L19, 0) | P19: =IFERROR(M19/$M$6, 0) | Q19: 0.04 | R19: =P19-Q19 | S19: 2023-01-20 | T19: Inflation & currency devaluation hedge
... A22: INV-015 | B22: High Yield Treasury Cash | C22: CASH | D22: Cash | E22: Cash & Cash Eq | F22: Liquid Reserves | G22: United States | H22: Fidelity | I22: 1 | J22: 10000 | K22: 10000 | L22: =I22*J22 | M22: =I22*K22 | N22: =M22-L22 | O22: =IFERROR(N22/L22, 0) | P22: =IFERROR(M22/$M$6, 0) | Q22: 0.01 | R22: =P22-Q22 | S22: 2023-01-01 | T22: Dry powder emergency liquidity

Sheet 04_Transactions
A1: =HYPERLINK("#01_Start_Here!A1", "🏠 Start") | B1: =HYPERLINK("#02_Dashboard!A1", "📊 Dashboard") | C1: =HYPERLINK("#03_Holdings!A1", "💼 Holdings") | D1: =HYPERLINK("#04_Transactions!A1", "📑 Ledger") | E1: =HYPERLINK("#05_Performance!A1", "📈 Performance") | F1: =HYPERLINK("#06_Allocation_Risk!A1", "🎯 Allocation") | G1: =HYPERLINK("#07_Dividends_Income!A1", "💰 Dividends") | H1: =HYPERLINK("#08_Goals_SIP!A1", "🎯 Goals") | I1: =HYPERLINK("#09_Rebalancing_Drift!A1", "⚖️ Rebalance") | J1: =HYPERLINK("#10_Scenarios_Freedom!A1", "🚀 What-If") | K1: =HYPERLINK("#11_Reviews_Reports!A1", "📋 Reports") | L1: =HYPERLINK("#12_Investment_Journal!A1", "📓 Journal") | M1: =HYPERLINK("#13_Settings_Assumptions!A1", "⚙️ Settings")
A3: INVESTMENT TRANSACTION LEDGER
A4: Chronological Record of Buys, Sells, Dividends, Splits, Fees & Cash Flows
A6: TRANSACTION LEDGER TOTALS | E6: Total Fees: | F6: =SUM(H8:H30) | G6: Total Taxes: | H6: =SUM(I8:I30) | I6: Total Trx Value: | J6: =SUM(J8:J30) | K6: Booked Realized P/L: | L6: =SUM(L8:L30)
A7: Tx ID | B7: Date | C7: Investment / Holding | D7: Ticker | E7: Transaction Type | F7: Quantity | G7: Price / Unit | H7: Fees ($) | I7: Taxes ($) | J7: Gross Value | K7: Cash Flow (+/-) | L7: Realized Gain/Loss | M7: Trade Notes & Thesis
A8: TX-1001 | B8: 2023-01-15 | C8: Apple Inc. | D8: AAPL | E8: Buy | F8: 50 | G8: 170 | H8: 2.5 | I8: 0.5 | J8: =F8*G8 | K8: =IF(OR(E8="Buy",E8="Fee",E8="Withdrawal"), -(J8+H8+I8), IF(OR(E8="Sell",E8="Dividend"), J8-H8-I8, J8)) | L8: =IF(E8="Sell", (F8*G8)-H8-I8-(F8*165.00), 0) | M8: Initial tech core position
A9: TX-1002 | B9: 2023-02-10 | C9: Microsoft Corp. | D9: MSFT | E9: Buy | F9: 30 | G9: 335 | H9: 2.5 | I9: 0.5 | J9: =F9*G9 | K9: =IF(OR(E9="Buy",E9="Fee",E9="Withdrawal"), -(J9+H9+I9), IF(OR(E9="Sell",E9="Dividend"), J9-H9-I9, J9)) | L9: =IF(E9="Sell", (F9*G9)-H9-I9-(F9*165.00), 0) | M9: Cloud expansion thesis
A10: TX-1003 | B10: 2023-03-15 | C10: Apple Inc. | D10: AAPL | E10: Dividend | F10: 50 | G10: 0.24 | H10: 0 | I10: 1.8 | J10: =F10*G10 | K10: =IF(OR(E10="Buy",E10="Fee",E10="Withdrawal"), -(J10+H10+I10), IF(OR(E10="Sell",E10="Dividend"), J10-H10-I10, J10)) | L10: =IF(E10="Sell", (F10*G10)-H10-I10-(F10*165.00), 0) | M10: Quarterly cash dividend
A11: TX-1004 | B11: 2023-04-12 | C11: Alphabet Inc. | D11: GOOGL | E11: Buy | F11: 70 | G11: 132.8 | H11: 2.5 | I11: 0.5 | J11: =F11*G11 | K11: =IF(OR(E11="Buy",E11="Fee",E11="Withdrawal"), -(J11+H11+I11), IF(OR(E11="Sell",E11="Dividend"), J11-H11-I11, J11)) | L11: =IF(E11="Sell", (F11*G11)-H11-I11-(F11*165.00), 0) | M11: Valuation discount buy
A12: TX-1005 | B12: 2023-05-10 | C12: Vanguard S&P 500 ETF | D12: VOO | E12: Buy | F12: 60 | G12: 405 | H12: 0 | I12: 0 | J12: =F12*G12 | K12: =IF(OR(E12="Buy",E12="Fee",E12="Withdrawal"), -(J12+H12+I12), IF(OR(E12="Sell",E12="Dividend"), J12-H12-I12, J12)) | L12: =IF(E12="Sell", (F12*G12)-H12-I12-(F12*165.00), 0) | M12: Core index dollar cost averaging
A13: TX-1006 | B13: 2023-06-20 | C13: NVIDIA Corporation | D13: NVDA | E13: Buy | F13: 100 | G13: 42 | H13: 2.5 | I13: 0.5 | J13: =F13*G13 | K13: =IF(OR(E13="Buy",E13="Fee",E13="Withdrawal"), -(J13+H13+I13), IF(OR(E13="Sell",E13="Dividend"), J13-H13-I13, J13)) | L13: =IF(E13="Sell", (F13*G13)-H13-I13-(F13*165.00), 0) | M13: AI datacenter momentum
A14: TX-1007 | B14: 2023-07-22 | C14: Vanguard Total Bond Market | D14: BND | E14: Buy | F14: 180 | G14: 72.5 | H14: 0 | I14: 0 | J14: =F14*G14 | K14: =IF(OR(E14="Buy",E14="Fee",E14="Withdrawal"), -(J14+H14+I14), IF(OR(E14="Sell",E14="Dividend"), J14-H14-I14, J14)) | L14: =IF(E14="Sell", (F14*G14)-H14-I14-(F14*165.00), 0) | M14: Fixed income allocation
A15: TX-1008 | B15: 2023-08-15 | C15: JPMorgan Chase & Co. | D15: JPM | E15: Buy | F15: 35 | G15: 155 | H15: 2.5 | I15: 0.5 | J15: =F15*G15 | K15: =IF(OR(E15="Buy",E15="Fee",E15="Withdrawal"), -(J15+H15+I15), IF(OR(E15="Sell",E15="Dividend"), J15-H15-I15, J15)) | L15: =IF(E15="Sell", (F15*G15)-H15-I15-(F15*165.00), 0) | M15: Financials diversification
A16: TX-1009 | B16: 2023-09-10 | C16: Realty Income Corp. | D16: O | E16: Buy | F16: 150 | G16: 52.3 | H16: 2.5 | I16: 0.5 | J16: =F16*G16 | K16: =IF(OR(E16="Buy",E16="Fee",E16="Withdrawal"), -(J16+H16+I16), IF(OR(E16="Sell",E16="Dividend"), J16-H16-I16, J16)) | L16: =IF(E16="Sell", (F16*G16)-H16-I16-(F16*165.00), 0) | M16: Monthly income generator
A17: TX-1010 | B17: 2023-10-15 | C17: Apple Inc. | D17: AAPL | E17: Buy | F17: 35 | G17: 183.35 | H17: 2.5 | I17: 0.5 | J17: =F17*G17 | K17: =IF(OR(E17="Buy",E17="Fee",E17="Withdrawal"), -(J17+H17+I17), IF(OR(E17="Sell",E17="Dividend"), J17-H17-I17, J17)) | L17: =IF(E17="Sell", (F17*G17)-H17-I17-(F17*165.00), 0) | M17: Dip purchase on earnings
A18: TX-1011 | B18: 2023-11-28 | C18: Eli Lilly and Co. | D18: LLY | E18: Buy | F18: 15 | G18: 610 | H18: 2.5 | I18: 0.5 | J18: =F18*G18 | K18: =IF(OR(E18="Buy",E18="Fee",E18="Withdrawal"), -(J18+H18+I18), IF(OR(E18="Sell",E18="Dividend"), J18-H18-I18, J18)) | L18: =IF(E18="Sell", (F18*G18)-H18-I18-(F18*165.00), 0) | M18: Healthcare innovation
A19: TX-1012 | B19: 2024-02-14 | C19: Vanguard S&P 500 ETF | D19: VOO | E19: Buy | F19: 50 | G19: 416 | H19: 0 | I19: 0 | J19: =F19*G19 | K19: =IF(OR(E19="Buy",E19="Fee",E19="Withdrawal"), -(J19+H19+I19), IF(OR(E19="Sell",E19="Dividend"), J19-H19-I19, J19)) | L19: =IF(E19="Sell", (F19*G19)-H19-I19-(F19*165.00), 0) | M19: Scheduled annual bonus reinvestment
... A22: TX-1015 | B22: 2024-06-15 | C22: Microsoft Corp. | D22: MSFT | E22: Buy | F22: 15 | G22: 350.6 | H22: 2.5 | I22: 0.5 | J22: =F22*G22 | K22: =IF(OR(E22="Buy",E22="Fee",E22="Withdrawal"), -(J22+H22+I22), IF(OR(E22="Sell",E22="Dividend"), J22-H22-I22, J22)) | L22: =IF(E22="Sell", (F22*G22)-H22-I22-(F22*165.00), 0) | M22: Copilot enterprise adoption

Sheet 05_Performance
A1: =HYPERLINK("#01_Start_Here!A1", "🏠 Start") | B1: =HYPERLINK("#02_Dashboard!A1", "📊 Dashboard") | C1: =HYPERLINK("#03_Holdings!A1", "💼 Holdings") | D1: =HYPERLINK("#04_Transactions!A1", "📑 Ledger") | E1: =HYPERLINK("#05_Performance!A1", "📈 Performance") | F1: =HYPERLINK("#06_Allocation_Risk!A1", "🎯 Allocation") | G1: =HYPERLINK("#07_Dividends_Income!A1", "💰 Dividends") | H1: =HYPERLINK("#08_Goals_SIP!A1", "🎯 Goals") | I1: =HYPERLINK("#09_Rebalancing_Drift!A1", "⚖️ Rebalance") | J1: =HYPERLINK("#10_Scenarios_Freedom!A1", "🚀 What-If") | K1: =HYPERLINK("#11_Reviews_Reports!A1", "📋 Reports") | L1: =HYPERLINK("#12_Investment_Journal!A1", "📓 Journal") | M1: =HYPERLINK("#13_Settings_Assumptions!A1", "⚙️ Settings")
A3: PORTFOLIO PERFORMANCE & BENCHMARK ANALYTICS
A4: Time-Weighted (TWR), Money-Weighted (MWR / XIRR) Returns & Market Alpha Comparison
A6: TIME-WEIGHTED RETURN (TWR) | D6: MONEY-WEIGHTED (IRR / XIRR) | G6: BENCHMARK RETURN (S&P 500) | J6: NET ALPHA / OUTPERFORMANCE
A7: =F24 | D7: ='03_Holdings'!O6*1.08 | G7: =G24 | J7: =F24-G24
A8: Pure Manager Skill (Cash Neutral) | D8: Investor Personal Dollar Return | G8: Broad Market Index Baseline | J8: Excess Return Over Benchmark
A10: MONTH-BY-MONTH PORTFOLIO SNAPSHOTS & BENCHMARK COMPARISON | J10: HOW TO READ RETURNS (TWR vs MWR)
A11: Month | B11: Starting Value | C11: Net Inflows | D11: Ending Value | E11: Net Investment Gain | F11: Portfolio Return % | G11: S&P 500 Return % | H11: Outperformance | J11: Time-Weighted Return (TWR)
A12: Oct 2025 | B12: 148000 | C12: 2000 | D12: 153200 | E12: =D12-(B12+C12) | F12: =IFERROR(E12/(B12+0.5*C12), 0) | G12: 0.015 | H12: =F12-G12 | J12: Evaluates investment management performance independent of the timing and size of external deposits or withdrawals. Eliminates cash flow bias to reflect true portfolio manager compound skill.
A13: Nov 2025 | B13: 153200 | C13: 1500 | D13: 159800 | E13: =D13-(B13+C13) | F13: =IFERROR(E13/(B13+0.5*C13), 0) | G13: 0.022 | H13: =F13-G13
A14: Dec 2025 | B14: 159800 | C14: 3000 | D14: 168500 | E14: =D14-(B14+C14) | F14: =IFERROR(E14/(B14+0.5*C14), 0) | G14: 0.018 | H14: =F14-G14 | J14: Money-Weighted Return (MWR / IRR)
A15: Jan 2026 | B15: 168500 | C15: 2500 | D15: 174200 | E15: =D15-(B15+C15) | F15: =IFERROR(E15/(B15+0.5*C15), 0) | G15: 0.009 | H15: =F15-G15 | J15: Measures the actual personal annualized rate of return on every dollar invested, heavily sensitive to when cash was deposited. If you deposit heavily right before a bull market, MWR > TWR.
A16: Feb 2026 | B16: 174200 | C16: 1500 | D16: 181000 | E16: =D16-(B16+C16) | F16: =IFERROR(E16/(B16+0.5*C16), 0) | G16: 0.014 | H16: =F16-G16
A17: Mar 2026 | B17: 181000 | C17: 2000 | D17: 187400 | E17: =D17-(B17+C17) | F17: =IFERROR(E17/(B17+0.5*C17), 0) | G17: 0.016 | H17: =F17-G17 | J17: Alpha & Benchmark Comparison
A18: Apr 2026 | B18: 187400 | C18: 1500 | D18: 184900 | E18: =D18-(B18+C18) | F18: =IFERROR(E18/(B18+0.5*C18), 0) | G18: -0.012 | H18: =F18-G18 | J18: Positive Alpha indicates the portfolio generated higher risk-adjusted capital growth than holding the low-cost benchmark index.
A19: May 2026 | B19: 184900 | C19: 2500 | D19: 192800 | E19: =D19-(B19+C19) | F19: =IFERROR(E19/(B19+0.5*C19), 0) | G19: 0.025 | H19: =F19-G19
A20: Jun 2026 | B20: 192800 | C20: 2000 | D20: 199400 | E20: =D20-(B20+C20) | F20: =IFERROR(E20/(B20+0.5*C20), 0) | G20: 0.013 | H20: =F20-G20
A21: Jul 2026 | B21: 199400 | C21: 1500 | D21: 208300 | E21: =D21-(B21+C21) | F21: =IFERROR(E21/(B21+0.5*C21), 0) | G21: 0.019 | H21: =F21-G21
A22: Aug 2026 | B22: 208300 | C22: 2000 | D22: 214600 | E22: =D22-(B22+C22) | F22: =IFERROR(E22/(B22+0.5*C22), 0) | G22: 0.011 | H22: =F22-G22
A23: Sep 2026 | B23: 214600 | C23: 2500 | D23: 222950 | E23: =D23-(B23+C23) | F23: =IFERROR(E23/(B23+0.5*C23), 0) | G23: 0.017 | H23: =F23-G23
A24: FULL YEAR TOTALS | B24: =B12 | C24: =SUM(C12:C23) | D24: =D23 | E24: =SUM(E12:E23) | F24: =PRODUCT(1+F12:F23)-1 | G24: =PRODUCT(1+G12:G23)-1 | H24: =F24-G24

Sheet 06_Allocation_Risk
A1: =HYPERLINK("#01_Start_Here!A1", "🏠 Start") | B1: =HYPERLINK("#02_Dashboard!A1", "📊 Dashboard") | C1: =HYPERLINK("#03_Holdings!A1", "💼 Holdings") | D1: =HYPERLINK("#04_Transactions!A1", "📑 Ledger") | E1: =HYPERLINK("#05_Performance!A1", "📈 Performance") | F1: =HYPERLINK("#06_Allocation_Risk!A1", "🎯 Allocation") | G1: =HYPERLINK("#07_Dividends_Income!A1", "💰 Dividends") | H1: =HYPERLINK("#08_Goals_SIP!A1", "🎯 Goals") | I1: =HYPERLINK("#09_Rebalancing_Drift!A1", "⚖️ Rebalance") | J1: =HYPERLINK("#10_Scenarios_Freedom!A1", "🚀 What-If") | K1: =HYPERLINK("#11_Reviews_Reports!A1", "📋 Reports") | L1: =HYPERLINK("#12_Investment_Journal!A1", "📓 Journal") | M1: =HYPERLINK("#13_Settings_Assumptions!A1", "⚙️ Settings")
A3: ASSET ALLOCATION, RISK & DIVERSIFICATION ANALYTICS
A4: Multi-Asset Distribution, Sector Exposures, Concentration Limits & Risk Volatility
A6: ASSET CLASS ALLOCATION & DRIFT MONITOR | G6: SECTOR BREAKDOWN
A7: Asset Class | B7: Current Value | C7: Weight % | D7: Target % | E7: Drift % | G7: Sector | H7: Current Value | I7: Weight % | J7: Concentration Warning
A8: Stocks (Equities) | B8: =SUMIFS('03_Holdings'!$M$8:$M$25, '03_Holdings'!$D$8:$D$25, "Stocks") | C8: =IFERROR(B8/$B$14, 0) | D8: 0.35 | E8: =C8-D8 | G8: Technology | H8: =SUMIFS('03_Holdings'!$M$8:$M$25, '03_Holdings'!$E$8:$E$25, "Technology") | I8: =IFERROR(H8/$B$14, 0) | J8: =IF(I8>0.30, "High Sector Concentration (>30%)", "Balanced Exposure")
A9: ETFs & Index Funds | B9: =SUMIFS('03_Holdings'!$M$8:$M$25, '03_Holdings'!$D$8:$D$25, "ETFs") | C9: =IFERROR(B9/$B$14, 0) | D9: 0.4 | E9: =C9-D9 | G9: Broad Index / Blended | H9: =SUMIFS('03_Holdings'!$M$8:$M$25, '03_Holdings'!$E$8:$E$25, "Broad Market") + SUMIFS('03_Holdings'!$M$8:$M$25, '03_Holdings'!$E$8:$E$25, "Technology Blend") | I9: =IFERROR(H9/$B$14, 0) | J9: =IF(I9>0.30, "High Sector Concentration (>30%)", "Balanced Exposure")
A10: Fixed Income / Bonds | B10: =SUMIFS('03_Holdings'!$M$8:$M$25, '03_Holdings'!$D$8:$D$25, "Bonds") | C10: =IFERROR(B10/$B$14, 0) | D10: 0.1 | E10: =C10-D10 | G10: Fixed Income / Gov | H10: =SUMIFS('03_Holdings'!$M$8:$M$25, '03_Holdings'!$E$8:$E$25, "Fixed Income") + SUMIFS('03_Holdings'!$M$8:$M$25, '03_Holdings'!$E$8:$E$25, "Government") | I10: =IFERROR(H10/$B$14, 0) | J10: =IF(I10>0.30, "High Sector Concentration (>30%)", "Balanced Exposure")
A11: Real Estate (REITs) | B11: =SUMIFS('03_Holdings'!$M$8:$M$25, '03_Holdings'!$D$8:$D$25, "REITs") | C11: =IFERROR(B11/$B$14, 0) | D11: 0.05 | E11: =C11-D11 | G11: Real Estate | H11: =SUMIFS('03_Holdings'!$M$8:$M$25, '03_Holdings'!$E$8:$E$25, "Real Estate") | I11: =IFERROR(H11/$B$14, 0) | J11: =IF(I11>0.30, "High Sector Concentration (>30%)", "Balanced Exposure")
A12: Gold & Commodities | B12: =SUMIFS('03_Holdings'!$M$8:$M$25, '03_Holdings'!$D$8:$D$25, "Gold") | C12: =IFERROR(B12/$B$14, 0) | D12: 0.05 | E12: =C12-D12 | G12: Healthcare | H12: =SUMIFS('03_Holdings'!$M$8:$M$25, '03_Holdings'!$E$8:$E$25, "Healthcare") | I12: =IFERROR(H12/$B$14, 0) | J12: =IF(I12>0.30, "High Sector Concentration (>30%)", "Balanced Exposure")
A13: Cash & Equivalents | B13: =SUMIFS('03_Holdings'!$M$8:$M$25, '03_Holdings'!$D$8:$D$25, "Cash") | C13: =IFERROR(B13/$B$14, 0) | D13: 0.05 | E13: =C13-D13 | G13: Financials | H13: =SUMIFS('03_Holdings'!$M$8:$M$25, '03_Holdings'!$E$8:$E$25, "Financials") | I13: =IFERROR(H13/$B$14, 0) | J13: =IF(I13>0.30, "High Sector Concentration (>30%)", "Balanced Exposure")
A14: TOTAL ALLOCATED | B14: =SUM(B8:B13) | C14: =SUM(C8:C13) | D14: =SUM(D8:D13) | E14: =C14-D14 | G14: Commodities / Gold | H14: =SUMIFS('03_Holdings'!$M$8:$M$25, '03_Holdings'!$E$8:$E$25, "Commodities") | I14: =IFERROR(H14/$B$14, 0) | J14: =IF(I14>0.30, "High Sector Concentration (>30%)", "Balanced Exposure")
G15: Cash & Liquid | H15: =SUMIFS('03_Holdings'!$M$8:$M$25, '03_Holdings'!$E$8:$E$25, "Cash & Cash Eq") | I15: =IFERROR(H15/$B$14, 0) | J15: =IF(I15>0.30, "High Sector Concentration (>30%)", "Balanced Exposure")
A17: PORTFOLIO CONCENTRATION METRICS | G17: DIVERSIFICATION INDEX & METHODOLOGY
A18: Top 1 Holding % | B18: =LARGE('03_Holdings'!P8:P22, 1) | C18: Largest single position exposure | G18: 88 / 100 | J18: EXCELLENT DIVERSIFICATION Multi-Asset + Multi-Sector Shield
A19: Top 3 Holdings % | B19: =SUM(LARGE('03_Holdings'!P8:P22, 1), LARGE('03_Holdings'!P8:P22, 2), LARGE('03_Holdings'!P8:P22, 3)) | C19: Top 3 weighted assets aggregate
A20: Top 5 Holdings % | B20: =SUM(LARGE('03_Holdings'!P8:P22, 1), LARGE('03_Holdings'!P8:P22, 2), LARGE('03_Holdings'!P8:P22, 3), LARGE('03_Holdings'!P8:P22, 4), LARGE('03_Holdings'!P8:P22, 5)) | C20: Top 5 weighted assets aggregate
A21: Largest Sector % | B21: =MAX(I8:I15) | C21: Highest single sector concentration | G21: Diversification Score Methodology: 1. Asset Class Count (6 active asset classes) = +30 pts 2. Top Holding Concentration Limit (<15% single holding) = +25 pts 3. Multi-Sector Spread (no sector > 35%) = +25 pts 4. Fixed Income & Cash Buffer Preservation = +10 pts Note: A high score represents structural diversification, not a guarantee against market drawdowns.
A22: Total Active Holdings | B22: =COUNTA('03_Holdings'!B8:B22) | C22: Count of diversified assets

Sheet 07_Dividends_Income
A1: =HYPERLINK("#01_Start_Here!A1", "🏠 Start") | B1: =HYPERLINK("#02_Dashboard!A1", "📊 Dashboard") | C1: =HYPERLINK("#03_Holdings!A1", "💼 Holdings") | D1: =HYPERLINK("#04_Transactions!A1", "📑 Ledger") | E1: =HYPERLINK("#05_Performance!A1", "📈 Performance") | F1: =HYPERLINK("#06_Allocation_Risk!A1", "🎯 Allocation") | G1: =HYPERLINK("#07_Dividends_Income!A1", "💰 Dividends") | H1: =HYPERLINK("#08_Goals_SIP!A1", "🎯 Goals") | I1: =HYPERLINK("#09_Rebalancing_Drift!A1", "⚖️ Rebalance") | J1: =HYPERLINK("#10_Scenarios_Freedom!A1", "🚀 What-If") | K1: =HYPERLINK("#11_Reviews_Reports!A1", "📋 Reports") | L1: =HYPERLINK("#12_Investment_Journal!A1", "📓 Journal") | M1: =HYPERLINK("#13_Settings_Assumptions!A1", "⚙️ Settings")
A3: DIVIDEND & PASSIVE CASHFLOW TRACKER
A4: Monthly Income Trajectory, Projected Annual Run-Rate & Yield on Cost
A6: ANNUAL PROJECTED DIVIDENDS | C6: =SUM(G8:G22)*4 | E6: TOTAL HISTORICAL COLLECTED | G6: =SUM(G8:G22) | I6: PORTFOLIO DIVIDEND YIELD | K6: =IFERROR(C6/'03_Holdings'!M6, 0)
A7: Payment Date | B7: Investment Name | C7: Ticker | D7: Asset Type | E7: Shares Held | F7: Dividend / Share | G7: Gross Payout | H7: Withholding Tax | I7: Net Cash Received | J7: Yield on Cost % | K7: Reinvestment Action
A8: 2024-01-15 | B8: Realty Income Corp. | C8: O | D8: REITs | E8: 150 | F8: 0.256 | G8: =E8*F8 | H8: 0 | I8: =G8-H8 | J8: =IFERROR((G8*4)/('03_Holdings'!L8), 0) | K8: Reinvested / DRIP
A9: 2024-02-15 | B9: Realty Income Corp. | C9: O | D9: REITs | E9: 150 | F9: 0.256 | G9: =E9*F9 | H9: 0 | I9: =G9-H9 | J9: =IFERROR((G9*4)/('03_Holdings'!L8), 0) | K9: Reinvested / DRIP
A10: 2024-03-15 | B10: Apple Inc. | C10: AAPL | D10: Stocks | E10: 85 | F10: 0.25 | G10: =E10*F10 | H10: 3.19 | I10: =G10-H10 | J10: =IFERROR((G10*4)/('03_Holdings'!L8), 0) | K10: Paid to Cash Buffer
A11: 2024-03-22 | B11: Vanguard S&P 500 ETF | C11: VOO | D11: ETFs | E11: 110 | F11: 1.54 | G11: =E11*F11 | H11: 0 | I11: =G11-H11 | J11: =IFERROR((G11*4)/('03_Holdings'!L8), 0) | K11: Reinvested / DRIP
A12: 2024-03-28 | B12: Microsoft Corp. | C12: MSFT | D12: Stocks | E12: 45 | F12: 0.75 | G12: =E12*F12 | H12: 5.06 | I12: =G12-H12 | J12: =IFERROR((G12*4)/('03_Holdings'!L8), 0) | K12: Paid to Cash Buffer
A13: 2024-04-15 | B13: Realty Income Corp. | C13: O | D13: REITs | E13: 150 | F13: 0.256 | G13: =E13*F13 | H13: 0 | I13: =G13-H13 | J13: =IFERROR((G13*4)/('03_Holdings'!L8), 0) | K13: Reinvested / DRIP
A14: 2024-05-15 | B14: Realty Income Corp. | C14: O | D14: REITs | E14: 150 | F14: 0.256 | G14: =E14*F14 | H14: 0 | I14: =G14-H14 | J14: =IFERROR((G14*4)/('03_Holdings'!L8), 0) | K14: Reinvested / DRIP
A15: 2024-06-15 | B15: Apple Inc. | C15: AAPL | D15: Stocks | E15: 85 | F15: 0.25 | G15: =E15*F15 | H15: 3.19 | I15: =G15-H15 | J15: =IFERROR((G15*4)/('03_Holdings'!L8), 0) | K15: Paid to Cash Buffer
A16: 2024-06-22 | B16: Vanguard S&P 500 ETF | C16: VOO | D16: ETFs | E16: 110 | F16: 1.62 | G16: =E16*F16 | H16: 0 | I16: =G16-H16 | J16: =IFERROR((G16*4)/('03_Holdings'!L8), 0) | K16: Reinvested / DRIP
A17: 2024-06-28 | B17: Microsoft Corp. | C17: MSFT | D17: Stocks | E17: 45 | F17: 0.75 | G17: =E17*F17 | H17: 5.06 | I17: =G17-H17 | J17: =IFERROR((G17*4)/('03_Holdings'!L8), 0) | K17: Paid to Cash Buffer
A18: 2024-07-15 | B18: Realty Income Corp. | C18: O | D18: REITs | E18: 150 | F18: 0.256 | G18: =E18*F18 | H18: 0 | I18: =G18-H18 | J18: =IFERROR((G18*4)/('03_Holdings'!L8), 0) | K18: Reinvested / DRIP
A19: 2024-08-15 | B19: Realty Income Corp. | C19: O | D19: REITs | E19: 150 | F19: 0.256 | G19: =E19*F19 | H19: 0 | I19: =G19-H19 | J19: =IFERROR((G19*4)/('03_Holdings'!L8), 0) | K19: Reinvested / DRIP

Sheet 08_Goals_SIP
A1: =HYPERLINK("#01_Start_Here!A1", "🏠 Start") | B1: =HYPERLINK("#02_Dashboard!A1", "📊 Dashboard") | C1: =HYPERLINK("#03_Holdings!A1", "💼 Holdings") | D1: =HYPERLINK("#04_Transactions!A1", "📑 Ledger") | E1: =HYPERLINK("#05_Performance!A1", "📈 Performance") | F1: =HYPERLINK("#06_Allocation_Risk!A1", "🎯 Allocation") | G1: =HYPERLINK("#07_Dividends_Income!A1", "💰 Dividends") | H1: =HYPERLINK("#08_Goals_SIP!A1", "🎯 Goals") | I1: =HYPERLINK("#09_Rebalancing_Drift!A1", "⚖️ Rebalance") | J1: =HYPERLINK("#10_Scenarios_Freedom!A1", "🚀 What-If") | K1: =HYPERLINK("#11_Reviews_Reports!A1", "📋 Reports") | L1: =HYPERLINK("#12_Investment_Journal!A1", "📓 Journal") | M1: =HYPERLINK("#13_Settings_Assumptions!A1", "⚙️ Settings")
A3: INVESTMENT GOALS & RECURRING SIP TRACKER
A4: Financial Milestone Progress, Target Dates, Required Monthly SIP & Execution Compliance
A6: PORTFOLIO GOALS & MILESTONE ROADMAP
A7: Goal Name | B7: Target Amount | C7: Current Saved | D7: Target Date | E7: Years Left | F7: Priority | G7: Exp Return | H7: Progress % | I7: Req Monthly SIP | J7: Status | K7: Action Recommendation
A8: Financial Freedom / FIRE | B8: 1200000 | C8: 145000 | D8: 2036-12-31 | E8: 10 | F8: High | G8: 0.09 | H8: =IFERROR(C8/B8, 0) | I8: =IFERROR(PMT(G8/12, E8*12, -C8, B8), 0) | J8: =IF(H8>=1, "Completed", IF(H8>=0.4, "On Track", "Needs Attention")) | K8: ="Save " & TEXT(I8, "$#,##0") & "/mo at " & TEXT(G8, "0%") & " CAGR"
A9: Dream Home Down Payment | B9: 250000 | C9: 60000 | D9: 2029-06-30 | E9: 3 | F9: High | G9: 0.07 | H9: =IFERROR(C9/B9, 0) | I9: =IFERROR(PMT(G9/12, E9*12, -C9, B9), 0) | J9: =IF(H9>=1, "Completed", IF(H9>=0.4, "On Track", "Needs Attention")) | K9: ="Save " & TEXT(I9, "$#,##0") & "/mo at " & TEXT(G9, "0%") & " CAGR"
A10: Child Higher Education Fund | B10: 180000 | C10: 32000 | D10: 2034-08-31 | E10: 8 | F10: Medium | G10: 0.08 | H10: =IFERROR(C10/B10, 0) | I10: =IFERROR(PMT(G10/12, E10*12, -C10, B10), 0) | J10: =IF(H10>=1, "Completed", IF(H10>=0.4, "On Track", "Needs Attention")) | K10: ="Save " & TEXT(I10, "$#,##0") & "/mo at " & TEXT(G10, "0%") & " CAGR"
A11: Emergency Ballast Fund | B11: 50000 | C11: 25000 | D11: 2027-12-31 | E11: 1.5 | F11: Crucial | G11: 0.05 | H11: =IFERROR(C11/B11, 0) | I11: =IFERROR(PMT(G11/12, E11*12, -C11, B11), 0) | J11: =IF(H11>=1, "Completed", IF(H11>=0.4, "On Track", "Needs Attention")) | K11: ="Save " & TEXT(I11, "$#,##0") & "/mo at " & TEXT(G11, "0%") & " CAGR"
A12: Luxury Sabbatical / World Trip | B12: 35000 | C12: 12000 | D12: 2028-05-31 | E12: 2 | F12: Low | G12: 0.07 | H12: =IFERROR(C12/B12, 0) | I12: =IFERROR(PMT(G12/12, E12*12, -C12, B12), 0) | J12: =IF(H12>=1, "Completed", IF(H12>=0.4, "On Track", "Needs Attention")) | K12: ="Save " & TEXT(I12, "$#,##0") & "/mo at " & TEXT(G12, "0%") & " CAGR"
A15: MONTHLY SIP CONTRIBUTION EXECUTION & COMPLIANCE
A16: Month | B16: Planned Contribution | C16: Actual Invested | D16: Difference ($) | E16: Variance % | F16: Execution Status | G16: Notes
A17: Jan 2026 | B17: 2500 | C17: 2500 | D17: =C17-B17 | E17: =IFERROR(D17/B17, 0) | F17: =IF(D17>=0, "100% Compliant", "Underfunded") | G17: Fully funded
A18: Feb 2026 | B18: 2500 | C18: 2500 | D18: =C18-B18 | E18: =IFERROR(D18/B18, 0) | F18: =IF(D18>=0, "100% Compliant", "Underfunded") | G18: Fully funded
A19: Mar 2026 | B19: 2500 | C19: 2750 | D19: =C19-B19 | E19: =IFERROR(D19/B19, 0) | F19: =IF(D19>=0, "100% Compliant", "Underfunded") | G19: Extra bonus allocation
A20: Apr 2026 | B20: 2500 | C20: 2000 | D20: =C20-B20 | E20: =IFERROR(D20/B20, 0) | F20: =IF(D20>=0, "100% Compliant", "Underfunded") | G20: Vehicle maintenance expense
A21: May 2026 | B21: 2500 | C21: 2500 | D21: =C21-B21 | E21: =IFERROR(D21/B21, 0) | F21: =IF(D21>=0, "100% Compliant", "Underfunded") | G21: Fully funded
A22: Jun 2026 | B22: 2500 | C22: 3000 | D22: =C22-B22 | E22: =IFERROR(D22/B22, 0) | F22: =IF(D22>=0, "100% Compliant", "Underfunded") | G22: Quarterly incentive contribution
A23: Jul 2026 | B23: 2500 | C23: 2500 | D23: =C23-B23 | E23: =IFERROR(D23/B23, 0) | F23: =IF(D23>=0, "100% Compliant", "Underfunded") | G23: Fully funded
A24: Aug 2026 | B24: 2500 | C24: 2500 | D24: =C24-B24 | E24: =IFERROR(D24/B24, 0) | F24: =IF(D24>=0, "100% Compliant", "Underfunded") | G24: Fully funded
A25: Sep 2026 | B25: 2500 | C25: 2500 | D25: =C25-B25 | E25: =IFERROR(D25/B25, 0) | F25: =IF(D25>=0, "100% Compliant", "Underfunded") | G25: Fully funded

Sheet 09_Rebalancing_Drift
A1: =HYPERLINK("#01_Start_Here!A1", "🏠 Start") | B1: =HYPERLINK("#02_Dashboard!A1", "📊 Dashboard") | C1: =HYPERLINK("#03_Holdings!A1", "💼 Holdings") | D1: =HYPERLINK("#04_Transactions!A1", "📑 Ledger") | E1: =HYPERLINK("#05_Performance!A1", "📈 Performance") | F1: =HYPERLINK("#06_Allocation_Risk!A1", "🎯 Allocation") | G1: =HYPERLINK("#07_Dividends_Income!A1", "💰 Dividends") | H1: =HYPERLINK("#08_Goals_SIP!A1", "🎯 Goals") | I1: =HYPERLINK("#09_Rebalancing_Drift!A1", "⚖️ Rebalance") | J1: =HYPERLINK("#10_Scenarios_Freedom!A1", "🚀 What-If") | K1: =HYPERLINK("#11_Reviews_Reports!A1", "📋 Reports") | L1: =HYPERLINK("#12_Investment_Journal!A1", "📓 Journal") | M1: =HYPERLINK("#13_Settings_Assumptions!A1", "⚙️ Settings")
A3: AUTOMATED PORTFOLIO REBALANCING ENGINE
A4: Drift Tolerance Bands, Tax-Efficient Buy/Sell Guidance & Fresh Cash Allocator
A6: ACCEPTABLE ALLOCATION DRIFT BAND | D6: 0.05 | E6: Positions drifting more than ±5.0% from target will trigger a 'Rebalance Alert' warning.
A8: Asset Class | B8: Current Value | C8: Current % | D8: Target % | E8: Drift % | F8: Target Value ($) | G8: Action | H8: Rebalance Amount | I8: Smart Cash Inflow Buy | J8: Drift Status | K8: Planning Guidance
A9: Stocks (Equities) | B9: ='06_Allocation_Risk'!B8 | C9: ='06_Allocation_Risk'!C8 | D9: ='06_Allocation_Risk'!D8 | E9: =C9-D9 | F9: =D9*'03_Holdings'!$M$6 | G9: =IF(ABS(E9)<=$D$6, "HOLD", IF(E9>0, "SELL", "BUY")) | H9: =F9-B9 | I9: =IF(H9>0, H9, 0) | J9: =IF(ABS(E9)<=$D$6, "Within Target", IF(ABS(E9)<=0.08, "Monitor", "Rebalance Alert")) | K9: =IF(G9="SELL", "Consider trimming or directing new cash elsewhere", IF(G9="BUY", "Deploy new savings to restore balance", "Target weight on schedule"))
A10: ETFs & Index Funds | B10: ='06_Allocation_Risk'!B9 | C10: ='06_Allocation_Risk'!C9 | D10: ='06_Allocation_Risk'!D9 | E10: =C10-D10 | F10: =D10*'03_Holdings'!$M$6 | G10: =IF(ABS(E10)<=$D$6, "HOLD", IF(E10>0, "SELL", "BUY")) | H10: =F10-B10 | I10: =IF(H10>0, H10, 0) | J10: =IF(ABS(E10)<=$D$6, "Within Target", IF(ABS(E10)<=0.08, "Monitor", "Rebalance Alert")) | K10: =IF(G10="SELL", "Consider trimming or directing new cash elsewhere", IF(G10="BUY", "Deploy new savings to restore balance", "Target weight on schedule"))
A11: Fixed Income / Bonds | B11: ='06_Allocation_Risk'!B10 | C11: ='06_Allocation_Risk'!C10 | D11: ='06_Allocation_Risk'!D10 | E11: =C11-D11 | F11: =D11*'03_Holdings'!$M$6 | G11: =IF(ABS(E11)<=$D$6, "HOLD", IF(E11>0, "SELL", "BUY")) | H11: =F11-B11 | I11: =IF(H11>0, H11, 0) | J11: =IF(ABS(E11)<=$D$6, "Within Target", IF(ABS(E11)<=0.08, "Monitor", "Rebalance Alert")) | K11: =IF(G11="SELL", "Consider trimming or directing new cash elsewhere", IF(G11="BUY", "Deploy new savings to restore balance", "Target weight on schedule"))
A12: Real Estate (REITs) | B12: ='06_Allocation_Risk'!B11 | C12: ='06_Allocation_Risk'!C11 | D12: ='06_Allocation_Risk'!D11 | E12: =C12-D12 | F12: =D12*'03_Holdings'!$M$6 | G12: =IF(ABS(E12)<=$D$6, "HOLD", IF(E12>0, "SELL", "BUY")) | H12: =F12-B12 | I12: =IF(H12>0, H12, 0) | J12: =IF(ABS(E12)<=$D$6, "Within Target", IF(ABS(E12)<=0.08, "Monitor", "Rebalance Alert")) | K12: =IF(G12="SELL", "Consider trimming or directing new cash elsewhere", IF(G12="BUY", "Deploy new savings to restore balance", "Target weight on schedule"))
A13: Gold & Commodities | B13: ='06_Allocation_Risk'!B12 | C13: ='06_Allocation_Risk'!C12 | D13: ='06_Allocation_Risk'!D12 | E13: =C13-D13 | F13: =D13*'03_Holdings'!$M$6 | G13: =IF(ABS(E13)<=$D$6, "HOLD", IF(E13>0, "SELL", "BUY")) | H13: =F13-B13 | I13: =IF(H13>0, H13, 0) | J13: =IF(ABS(E13)<=$D$6, "Within Target", IF(ABS(E13)<=0.08, "Monitor", "Rebalance Alert")) | K13: =IF(G13="SELL", "Consider trimming or directing new cash elsewhere", IF(G13="BUY", "Deploy new savings to restore balance", "Target weight on schedule"))
A14: Cash & Equivalents | B14: ='06_Allocation_Risk'!B13 | C14: ='06_Allocation_Risk'!C13 | D14: ='06_Allocation_Risk'!D13 | E14: =C14-D14 | F14: =D14*'03_Holdings'!$M$6 | G14: =IF(ABS(E14)<=$D$6, "HOLD", IF(E14>0, "SELL", "BUY")) | H14: =F14-B14 | I14: =IF(H14>0, H14, 0) | J14: =IF(ABS(E14)<=$D$6, "Within Target", IF(ABS(E14)<=0.08, "Monitor", "Rebalance Alert")) | K14: =IF(G14="SELL", "Consider trimming or directing new cash elsewhere", IF(G14="BUY", "Deploy new savings to restore balance", "Target weight on schedule"))
A15: PORTFOLIO TOTAL | B15: =SUM(B9:B14) | C15: =SUM(C9:C14) | D15: =SUM(D9:D14) | E15: =SUM(E9:E14) | F15: =SUM(F9:F14) | G15: - | H15: =SUM(H9:H14) | I15: =SUM(I9:I14) | J15: - | K15: Net Trade Delta Reconciled

Sheet 10_Scenarios_Freedom
A1: =HYPERLINK("#01_Start_Here!A1", "🏠 Start") | B1: =HYPERLINK("#02_Dashboard!A1", "📊 Dashboard") | C1: =HYPERLINK("#03_Holdings!A1", "💼 Holdings") | D1: =HYPERLINK("#04_Transactions!A1", "📑 Ledger") | E1: =HYPERLINK("#05_Performance!A1", "📈 Performance") | F1: =HYPERLINK("#06_Allocation_Risk!A1", "🎯 Allocation") | G1: =HYPERLINK("#07_Dividends_Income!A1", "💰 Dividends") | H1: =HYPERLINK("#08_Goals_SIP!A1", "🎯 Goals") | I1: =HYPERLINK("#09_Rebalancing_Drift!A1", "⚖️ Rebalance") | J1: =HYPERLINK("#10_Scenarios_Freedom!A1", "🚀 What-If") | K1: =HYPERLINK("#11_Reviews_Reports!A1", "📋 Reports") | L1: =HYPERLINK("#12_Investment_Journal!A1", "📓 Journal") | M1: =HYPERLINK("#13_Settings_Assumptions!A1", "⚙️ Settings")
A3: WHAT-IF SCENARIO SIMULATOR & FIRE FINANCIAL FREEDOM PLANNER
A4: Long-Term Wealth Compounding Engine, Safe Withdrawal Rates & Retirement Freedom Runway
A6: 30-YEAR WEALTH COMPOUNDING SCENARIO COMPARISON | G6: FINANCIAL FREEDOM (FIRE) CALCULATOR
A7: Parameter / Horizon | B7: Scenario A: Baseline | C7: Scenario B: Double Savings | D7: Scenario C: High Growth | E7: Scenario D: Defensive | G7: Parameter | H7: Value | I7: Notes & Methodology
A8: Initial Investment ($) | B8: 50000 | C8: 50000 | D8: 50000 | E8: 50000 | G8: Desired Annual Living Expenses | H8: 60000 | I8: Annual spending budget in retirement
A9: Monthly Contribution ($) | B9: 1000 | C9: 2000 | D9: 1000 | E9: 1000 | G9: Safe Withdrawal Rate (SWR) | H9: 0.04 | I9: Standard 4% Trinity study rule
A10: Expected Annual Return | B10: 0.08 | C10: 0.08 | D10: 0.1 | E10: 0.06 | G10: Freedom Target Portfolio Number | H10: =H8/H9 | I10: Total net portfolio needed for financial independence
A11: Inflation Assumption | B11: 0.03 | C11: 0.03 | D11: 0.03 | E11: 0.03 | G11: Current Liquid Portfolio Value | H11: ='03_Holdings'!M6 | I11: Current invested capital
A12: Projected Value: Year 5 | B12: =-FV(B10/12, 5*12, B9, B8) | C12: =-FV(C10/12, 5*12, C9, C8) | D12: =-FV(D10/12, 5*12, D9, D8) | E12: =-FV(E10/12, 5*12, E9, E8) | G12: Remaining Gap to Freedom | H12: =MAX(0, H10-H11) | I12: Capital shortfall to bridge
A13: Projected Value: Year 10 | B13: =-FV(B10/12, 10*12, B9, B8) | C13: =-FV(C10/12, 10*12, C9, C8) | D13: =-FV(D10/12, 10*12, D9, D8) | E13: =-FV(E10/12, 10*12, E9, E8) | G13: FIRE Journey Completed % | H13: =IFERROR(H11/H10, 0) | I13: Current milestone percentage achieved
A14: Projected Value: Year 15 | B14: =-FV(B10/12, 15*12, B9, B8) | C14: =-FV(C10/12, 15*12, C9, C8) | D14: =-FV(D10/12, 15*12, D9, D8) | E14: =-FV(E10/12, 15*12, E9, E8) | G14: Monthly Investment Rate | H14: 2500 | I14: Ongoing monthly capital injection
A15: Projected Value: Year 20 | B15: =-FV(B10/12, 20*12, B9, B8) | C15: =-FV(C10/12, 20*12, C9, C8) | D15: =-FV(D10/12, 20*12, D9, D8) | E15: =-FV(E10/12, 20*12, E9, E8) | G15: Expected Compound Growth Rate | H15: 0.08 | I15: Assumed market compound rate
A16: Projected Value: Year 30 | B16: =-FV(B10/12, 30*12, B9, B8) | C16: =-FV(C10/12, 30*12, C9, C8) | D16: =-FV(D10/12, 30*12, D9, D8) | E16: =-FV(E10/12, 30*12, E9, E8) | G16: Estimated Years to Freedom | H16: =IFERROR(NPER(H15/12, -H14, -H11, H10)/12, 0) | I16: Time required to cross full freedom threshold

Sheet 11_Reviews_Reports
A1: =HYPERLINK("#01_Start_Here!A1", "🏠 Start") | B1: =HYPERLINK("#02_Dashboard!A1", "📊 Dashboard") | C1: =HYPERLINK("#03_Holdings!A1", "💼 Holdings") | D1: =HYPERLINK("#04_Transactions!A1", "📑 Ledger") | E1: =HYPERLINK("#05_Performance!A1", "📈 Performance") | F1: =HYPERLINK("#06_Allocation_Risk!A1", "🎯 Allocation") | G1: =HYPERLINK("#07_Dividends_Income!A1", "💰 Dividends") | H1: =HYPERLINK("#08_Goals_SIP!A1", "🎯 Goals") | I1: =HYPERLINK("#09_Rebalancing_Drift!A1", "⚖️ Rebalance") | J1: =HYPERLINK("#10_Scenarios_Freedom!A1", "🚀 What-If") | K1: =HYPERLINK("#11_Reviews_Reports!A1", "📋 Reports") | L1: =HYPERLINK("#12_Investment_Journal!A1", "📓 Journal") | M1: =HYPERLINK("#13_Settings_Assumptions!A1", "⚙️ Settings")
A3: PORTFOLIO PERIODIC REVIEWS & ANNUAL REPORT
A4: Commercial Print-Ready Performance Statements, Gain Summaries & Executive Review
A6: EXECUTIVE MONTHLY PORTFOLIO REVIEW (LATEST MONTH)
A7: Starting Portfolio Value | B7: ='05_Performance'!B23
A8: Net Capital Inflows / (Outflows) | B8: ='05_Performance'!C23
A9: Ending Portfolio Value | B9: ='05_Performance'!D23
A10: Net Portfolio Capital Gain / (Loss) | B10: ='05_Performance'!E23
A11: Monthly Return % | B11: ='05_Performance'!F23
A12: Benchmark Return (S&P 500) | B12: ='05_Performance'!G23
A13: Monthly Alpha / Difference | B13: ='05_Performance'!H23
A14: Top Performer of the Month | B14: ='03_Holdings'!B8
A16: ANNUAL INVESTMENT PERFORMANCE REPORT (FULL YEAR)
A17: Metric | C17: Value | F17: Performance Breakdown | H17: Value
A18: Beginning Wealth Balance | C18: ='05_Performance'!B12 | F18: Realized Trading Profit | H18: ='04_Transactions'!L6
A19: Total Annual Injections | C19: ='05_Performance'!C24 | F19: Unrealized Portfolio Gains | H19: ='03_Holdings'!N6
A20: Ending Wealth Balance | C20: ='05_Performance'!D23 | F20: Dividends & Income Collected | H20: ='07_Dividends_Income'!G6
A21: Net Total Portfolio Growth | C21: ='05_Performance'!E24 | F21: Portfolio Annual Return (TWR) | H21: ='05_Performance'!F24
A22: Benchmark Annual Return | C22: ='05_Performance'!G24 | F22: Net Annual Alpha Generated | H22: ='05_Performance'!H24

Sheet 12_Investment_Journal
A1: =HYPERLINK("#01_Start_Here!A1", "🏠 Start") | B1: =HYPERLINK("#02_Dashboard!A1", "📊 Dashboard") | C1: =HYPERLINK("#03_Holdings!A1", "💼 Holdings") | D1: =HYPERLINK("#04_Transactions!A1", "📑 Ledger") | E1: =HYPERLINK("#05_Performance!A1", "📈 Performance") | F1: =HYPERLINK("#06_Allocation_Risk!A1", "🎯 Allocation") | G1: =HYPERLINK("#07_Dividends_Income!A1", "💰 Dividends") | H1: =HYPERLINK("#08_Goals_SIP!A1", "🎯 Goals") | I1: =HYPERLINK("#09_Rebalancing_Drift!A1", "⚖️ Rebalance") | J1: =HYPERLINK("#10_Scenarios_Freedom!A1", "🚀 What-If") | K1: =HYPERLINK("#11_Reviews_Reports!A1", "📋 Reports") | L1: =HYPERLINK("#12_Investment_Journal!A1", "📓 Journal") | M1: =HYPERLINK("#13_Settings_Assumptions!A1", "⚙️ Settings")
A3: INVESTMENT DECISION JOURNAL & TRADE THESIS LOG
A4: Disciplined Record of Investment Hypotheses, Conviction Levels, Exit Rules & Post-Mortems
A6: Entry ID | B6: Date | C6: Asset / Ticker | D6: Decision | E6: Core Investment Thesis & Catalyst | F6: Expected Horizon | G6: Conviction (1-5★) | H6: Exit Rules / Target | I6: Actual Outcome / Review Notes
A7: JRN-001 | B7: 2023-01-15 | C7: AAPL | D7: Buy | E7: Hardware ecosystem lock-in + Services margin expansion + High free cashflow | F7: 5+ Years | G7: ★★★★★ | H7: Trim if P/E exceeds 38x | I7: Strong multi-year gain; held core position
A8: JRN-002 | B8: 2023-02-10 | C8: MSFT | D8: Buy | E8: Enterprise software moat + Azure cloud growth + Generative AI integration | F8: 5+ Years | G8: ★★★★★ | H8: Hold indefinitely | I8: Outstanding compounder; beating expectations
A9: JRN-003 | B9: 2023-06-20 | C9: NVDA | D9: Buy | E9: Data center GPU computing monopoly; CUDA proprietary software moat | F9: 3-5 Years | G9: ★★★★☆ | H9: Rebalance if position exceeds 10% | I9: Extremely rapid appreciation; rebalanced once
A10: JRN-004 | B10: 2023-09-10 | C10: O | D10: Buy | E10: Predictable monthly cashflow dividend; triple-net retail lease tenants | F10: Income Focus | G10: ★★★★☆ | H10: Re-evaluate if occupancy drops < 95% | I10: Consistent monthly cash distributions
A11: JRN-005 | B11: 2024-05-18 | C11: TSLA | D11: Sell | E11: Electric vehicle margin compression + elevated robotaxi execution risk | F11: Closed | G11: ★★★☆☆ | H11: Reallocate proceeds to S&P 500 ETF | I11: Disciplined exit; protected booked capital

Sheet 13_Settings_Assumptions
A1: =HYPERLINK("#01_Start_Here!A1", "🏠 Start") | B1: =HYPERLINK("#02_Dashboard!A1", "📊 Dashboard") | C1: =HYPERLINK("#03_Holdings!A1", "💼 Holdings") | D1: =HYPERLINK("#04_Transactions!A1", "📑 Ledger") | E1: =HYPERLINK("#05_Performance!A1", "📈 Performance") | F1: =HYPERLINK("#06_Allocation_Risk!A1", "🎯 Allocation") | G1: =HYPERLINK("#07_Dividends_Income!A1", "💰 Dividends") | H1: =HYPERLINK("#08_Goals_SIP!A1", "🎯 Goals") | I1: =HYPERLINK("#09_Rebalancing_Drift!A1", "⚖️ Rebalance") | J1: =HYPERLINK("#10_Scenarios_Freedom!A1", "🚀 What-If") | K1: =HYPERLINK("#11_Reviews_Reports!A1", "📋 Reports") | L1: =HYPERLINK("#12_Investment_Journal!A1", "📓 Journal") | M1: =HYPERLINK("#13_Settings_Assumptions!A1", "⚙️ Settings")
A3: SYSTEM SETTINGS, ASSUMPTIONS & LOOKUP CATALOG
A4: Global Currencies, Benchmark Symbols, Rebalancing Bands & Data Validation Catalogs
A6: GLOBAL WORKBOOK PARAMETERS | F6: MASTER DROPDOWN LOOKUP CATALOGS
A7: Base Reporting Currency | B7: USD ($) | C7: Select reporting currency ($ USD, ₹ INR, € EUR, £ GBP) | F7: Asset Types | G7: Sectors | H7: Transaction Types | I7: Brokers / Accounts | J7: Currencies
A8: Current Portfolio Valuation Date | B8: 2026-09-07 | C8: Valuation snapshot date | F8: Stocks | G8: Technology | H8: Buy | I8: Fidelity | J8: USD ($)
A9: Primary Benchmark Index | B9: S&P 500 Index (SPY / VOO) | C9: Default benchmark for alpha calculations | F9: ETFs | G9: Broad Market | H9: Sell | I9: Charles Schwab | J9: INR (₹)
A10: Secondary Benchmark Index | B10: MSCI ACWI All-World ETF | C10: Global equity comparison benchmark | F10: Mutual Funds | G10: Technology Blend | H10: Dividend | I10: Interactive Brokers | J10: EUR (€)
A11: Rebalance Drift Threshold | B11: 0.05 | C11: Band beyond which rebalancing is recommended (±5.0%) | F11: Bonds | G11: International | H11: Interest | I11: Vanguard | J11: GBP (£)
A12: Cost Basis Calculation Mode | B12: Weighted Average Cost (WAC) | C12: Assumed tax-lot inventory method | F12: REITs | G12: Fixed Income | H12: Fee | I12: Zerodha | J12: CAD ($)
A13: Liquid Emergency Cash Buffer | B13: 10000 | C13: Uninvested capital preserved in liquid yields | F13: Gold | G13: Government | H13: Deposit | I13: Robinhood | J13: AUD ($)
F14: Cash | G14: Real Estate | H14: Withdrawal | I14: Local Broker
F15: Other | G15: Commodities | H15: Split
G16: Healthcare | H16: Bonus
G17: Financials | H17: Other
G18: Consumer
G19: Energy
